{
	"platform" : "android",
	"bundle" : "",
	"identifier" : "com.csair.impc",
	"name" : "统一移动平台",
	"version" : "1.1",
	"build" : 1,
	"releaseNote" : "1.1: Speed Boost. 1.0: First Release",
	"icon" : "http://xxx.com/image/a.png",
	"modifiedAt" : "2013-01-30 09:26:40",
	"modules":[
		
		{
             "privileges": [],
             "bundle": "",
             "showPushMsgCount": 0,
             "isAutoShow": false,
             "category": "站长A",
             "icon": "T13tJTByJT1RCvBVdK",
             "version": "1.0.0.153",
             "sortingWeight": 1,
             "releaseNote": "1.界面调整",
             "identifier": "com.csair.deviceregist",
             "build": 1,
             "name": "设备注册",
             "hidden": true,
             "autoDownload": false
        }

	]
}